README.rst
setup.cfg
setup.py
geoblend/__init__.py
geoblend/coefficients.c
geoblend/coefficients_openmp.c
geoblend/coeffs.py
geoblend/coeffs_numba.py
geoblend/convolve.c
geoblend/openmp.c
geoblend/solver.py
geoblend/utilities.py
geoblend/vector.c
geoblend.egg-info/PKG-INFO
geoblend.egg-info/SOURCES.txt
geoblend.egg-info/dependency_links.txt
geoblend.egg-info/entry_points.txt
geoblend.egg-info/not-zip-safe
geoblend.egg-info/requires.txt
geoblend.egg-info/top_level.txt
geoblend/scripts/__init__.py
geoblend/scripts/cli.py