Metadata-Version: 1.0
Name: geoblend
Version: 0.2.3.dev0
Summary: Geo-aware poisson blending.
Home-page: https://github.com/kapadia/geoblend
Author: Amit Kapadia
Author-email: amit@planet.com
License: MIT
Platform: UNKNOWN
